{
  "report_id": "research_20250801_151650",
  "timestamp": "2025-08-01T15:16:50.132793",
  "research_summary": {
    "total_opportunities_found": 9,
    "research_areas_covered": 5,
    "confidence_level": "high",
    "research_quality": "ai_powered_analysis"
  },
  "market_research": {
    "timestamp": "2025-08-01T15:16:50.132737",
    "research_areas": [
      {
        "research_type": "trending_stocks",
        "opportunities": [
          {
            "category": "trending_stocks",
            "opportunity": "NVDA - AI chip demand surge",
            "thesis": "Continued AI infrastructure buildout driving demand",
            "risk_level": "Medium",
            "time_horizon": "3-6 months",
            "research_confidence": "High"
          },
          {
            "category": "trending_stocks",
            "opportunity": "TSLA - EV market expansion",
            "thesis": "Global EV adoption accelerating, production scaling",
            "risk_level": "High",
            "time_horizon": "6-12 months",
            "research_confidence": "Medium"
          }
        ],
        "analysis_quality": "ai_powered",
        "last_updated": "2025-08-01T15:16:30.932467"
      },
      {
        "research_type": "crypto_opportunities",
        "opportunities": [
          {
            "category": "crypto",
            "opportunity": "BTC - Institutional adoption",
            "thesis": "ETF approvals driving institutional inflows",
            "risk_level": "Medium-High",
            "time_horizon": "3-12 months",
            "research_confidence": "High"
          },
          {
            "category": "crypto",
            "opportunity": "ETH - Staking rewards",
            "thesis": "Post-merge staking yields attractive vs traditional assets",
            "risk_level": "High",
            "time_horizon": "6-18 months",
            "research_confidence": "Medium"
          }
        ],
        "market_sentiment": "cautiously_optimistic",
        "last_updated": "2025-08-01T15:16:50.132299"
      },
      {
        "research_type": "sector_trends",
        "opportunities": [
          {
            "category": "sector_trend",
            "opportunity": "AI and Automation sector momentum",
            "thesis": "Strong fundamentals and growth trajectory in AI and Automation",
            "risk_level": "Medium",
            "time_horizon": "6-24 months",
            "research_confidence": "Medium"
          },
          {
            "category": "sector_trend",
            "opportunity": "Clean Energy sector momentum",
            "thesis": "Strong fundamentals and growth trajectory in Clean Energy",
            "risk_level": "Medium",
            "time_horizon": "6-24 months",
            "research_confidence": "Medium"
          },
          {
            "category": "sector_trend",
            "opportunity": "Biotech and Healthcare sector momentum",
            "thesis": "Strong fundamentals and growth trajectory in Biotech and Healthcare",
            "risk_level": "Medium",
            "time_horizon": "6-24 months",
            "research_confidence": "Medium"
          }
        ],
        "sectors_analyzed": [
          "AI and Automation",
          "Clean Energy",
          "Biotech and Healthcare",
          "Cybersecurity",
          "Cloud Computing",
          "Electric Vehicles",
          "Real Estate (REITs)"
        ],
        "last_updated": "2025-08-01T15:16:50.132487"
      },
      {
        "research_type": "economic_indicators",
        "opportunities": [
          {
            "category": "macro_trend",
            "opportunity": "Interest rate cycle positioning",
            "thesis": "Fed policy changes creating sector rotation opportunities",
            "risk_level": "Medium",
            "time_horizon": "3-12 months",
            "research_confidence": "High"
          }
        ],
        "indicators_analyzed": [
          "Federal Reserve policy changes",
          "Inflation trends and impact",
          "Employment data analysis",
          "GDP growth projections",
          "Currency strength analysis"
        ],
        "last_updated": "2025-08-01T15:16:50.132614"
      },
      {
        "research_type": "earnings_calendar",
        "opportunities": [
          {
            "category": "earnings_play",
            "opportunity": "Tech earnings season positioning",
            "thesis": "Strong guidance expected from major tech companies",
            "risk_level": "Medium-High",
            "time_horizon": "1-3 months",
            "research_confidence": "Medium"
          }
        ],
        "upcoming_catalysts": [
          "Tech earnings",
          "Fed meeting",
          "Economic data releases"
        ],
        "last_updated": "2025-08-01T15:16:50.132732"
      }
    ],
    "total_opportunities": 9
  },
  "investment_themes": [
    "AI and Technology Growth",
    "Cryptocurrency Institutional Adoption",
    "Sector Rotation Opportunities",
    "Macro Economic Positioning",
    "Earnings-Driven Catalysts"
  ],
  "risk_assessment": {
    "market_risk_level": "moderate",
    "key_risks": [
      "Interest rate changes",
      "Geopolitical tensions",
      "Market volatility"
    ],
    "risk_mitigation": "Diversification across asset classes and time horizons"
  },
  "recommendations": [
    {
      "recommendation": "Focus on AI/Tech sector opportunities",
      "rationale": "Strong fundamentals and growth trajectory",
      "allocation_suggestion": "30-40% of portfolio"
    },
    {
      "recommendation": "Consider crypto exposure with Bitcoin/Ethereum",
      "rationale": "Institutional adoption driving long-term value",
      "allocation_suggestion": "5-10% of portfolio"
    },
    {
      "recommendation": "Monitor interest rate sensitive sectors",
      "rationale": "Fed policy changes creating opportunities",
      "allocation_suggestion": "Tactical allocation based on policy"
    }
  ]
}