[
  {
    "source": "tinyman",
    "protocol_name": "Tinyman V2",
    "opportunity_type": "dex_trading",
    "description": "High liquidity pool: ALGO-USDC",
    "opportunity_score": 74.79025597450902,
    "risk_level": "low",
    "estimated_apy": 15.616040009763871,
    "liquidity": 4790255.974509023,
    "volume_24h": 1088950.666852193,
    "asset1": "ALGO",
    "asset2": "USDC",
    "pool_data": {
      "pool_id": "ALGO-USDC",
      "asset1_id": 0,
      "asset2_id": 31566704,
      "asset1_name": "ALGO",
      "asset2_name": "USDC",
      "liquidity": 4790255.974509023,
      "volume_24h": 1088950.666852193,
      "apy": 15.616040009763871,
      "fee": 0.003,
      "last_updated": "2025-08-11T23:03:34.620186",
      "source": "blockchain"
    }
  },
  {
    "source": "tinyman",
    "protocol_name": "Tinyman V2",
    "opportunity_type": "dex_trading",
    "description": "High liquidity pool: ALGO-USDT",
    "opportunity_score": 73.00324671665595,
    "risk_level": "low",
    "estimated_apy": 14.07690555218067,
    "liquidity": 3003246.7166559487,
    "volume_24h": 802850.4185517115,
    "asset1": "ALGO",
    "asset2": "USDT",
    "pool_data": {
      "pool_id": "ALGO-USDT",
      "asset1_id": 0,
      "asset2_id": 312769,
      "asset1_name": "ALGO",
      "asset2_name": "USDT",
      "liquidity": 3003246.7166559487,
      "volume_24h": 802850.4185517115,
      "apy": 14.07690555218067,
      "fee": 0.003,
      "last_updated": "2025-08-11T23:03:34.620195",
      "source": "blockchain"
    }
  },
  {
    "source": "tinyman",
    "protocol_name": "Tinyman V2",
    "opportunity_type": "dex_trading",
    "description": "High liquidity pool: USDC-USDT",
    "opportunity_score": 72.06650731753497,
    "risk_level": "low",
    "estimated_apy": 8.803731582970306,
    "liquidity": 2066507.3175349687,
    "volume_24h": 494059.13314576406,
    "asset1": "USDC",
    "asset2": "USDT",
    "pool_data": {
      "pool_id": "USDC-USDT",
      "asset1_id": 31566704,
      "asset2_id": 312769,
      "asset1_name": "USDC",
      "asset2_name": "USDT",
      "liquidity": 2066507.3175349687,
      "volume_24h": 494059.13314576406,
      "apy": 8.803731582970306,
      "fee": 0.003,
      "last_updated": "2025-08-11T23:03:34.620200",
      "source": "blockchain"
    }
  },
  {
    "source": "pact_finance",
    "protocol_name": "Pact Finance",
    "opportunity_type": "yield_farming",
    "description": "Yield farming pool: ALGO-USDC Yield Farm",
    "opportunity_score": 69.27099448944531,
    "risk_level": "medium",
    "estimated_apy": 18.54198897889062,
    "tvl": 7938503.34787023,
    "volume_24h": 1430057.9234080762,
    "pool_name": "ALGO-USDC Yield Farm",
    "pool_data": {
      "pool_id": "ALGO-USDC-FARM",
      "name": "ALGO-USDC Yield Farm",
      "tvl": 7938503.34787023,
      "apy": 18.54198897889062,
      "volume_24h": 1430057.9234080762,
      "fee": 0.003,
      "asset1": "ALGO",
      "asset2": "USDC",
      "min_stake": 0.1,
      "max_stake": 1000,
      "lock_period": 0,
      "rewards_token": "PACT",
      "last_updated": "2025-08-11T23:03:34.620447",
      "source": "blockchain"
    }
  },
  {
    "source": "pact_finance",
    "protocol_name": "Pact Finance",
    "opportunity_type": "yield_farming",
    "description": "Yield farming pool: ALGO-USDT Yield Farm",
    "opportunity_score": 67.58499763083485,
    "risk_level": "medium",
    "estimated_apy": 15.169995261669689,
    "tvl": 4896422.938700944,
    "volume_24h": 667567.6318821944,
    "pool_name": "ALGO-USDT Yield Farm",
    "pool_data": {
      "pool_id": "ALGO-USDT-FARM",
      "name": "ALGO-USDT Yield Farm",
      "tvl": 4896422.938700944,
      "apy": 15.169995261669689,
      "volume_24h": 667567.6318821944,
      "fee": 0.003,
      "asset1": "ALGO",
      "asset2": "USDT",
      "min_stake": 0.1,
      "max_stake": 800,
      "lock_period": 0,
      "rewards_token": "PACT",
      "last_updated": "2025-08-11T23:03:34.620455",
      "source": "blockchain"
    }
  },
  {
    "source": "pact_finance",
    "protocol_name": "Pact Finance",
    "opportunity_type": "yield_farming",
    "description": "Yield farming pool: USDC-USDT Yield Farm",
    "opportunity_score": 66.29380834490448,
    "risk_level": "medium",
    "estimated_apy": 12.587616689808954,
    "tvl": 3103457.0901055043,
    "volume_24h": 545418.0344519466,
    "pool_name": "USDC-USDT Yield Farm",
    "pool_data": {
      "pool_id": "USDC-USDT-FARM",
      "name": "USDC-USDT Yield Farm",
      "tvl": 3103457.0901055043,
      "apy": 12.587616689808954,
      "volume_24h": 545418.0344519466,
      "fee": 0.003,
      "asset1": "USDC",
      "asset2": "USDT",
      "min_stake": 10,
      "max_stake": 500000,
      "lock_period": 0,
      "rewards_token": "PACT",
      "last_updated": "2025-08-11T23:03:34.620459",
      "source": "blockchain"
    }
  },
  {
    "source": "folks_finance",
    "protocol_name": "Folks Finance",
    "opportunity_type": "lending",
    "description": "Lending pool: ALGO Lending Pool",
    "opportunity_score": 58.91374085664028,
    "risk_level": "low",
    "estimated_apy": 7.8274817132805605,
    "tvl": 14535210.470922649,
    "utilization": 0.7512670534373327,
    "pool_name": "ALGO Lending Pool",
    "pool_data": {
      "pool_id": "ALGO-LENDING",
      "name": "ALGO Lending Pool",
      "tvl": 14535210.470922649,
      "apy": 7.8274817132805605,
      "borrow_apy": 11.326826479217754,
      "utilization": 0.7512670534373327,
      "collateral_factor": 0.8,
      "asset": "ALGO",
      "min_deposit": 0.1,
      "max_deposit": 10000,
      "liquidation_threshold": 0.85,
      "last_updated": "2025-08-11T23:03:34.620697",
      "source": "blockchain"
    }
  },
  {
    "source": "folks_finance",
    "protocol_name": "Folks Finance",
    "opportunity_type": "lending",
    "description": "Lending pool: USDC Lending Pool",
    "opportunity_score": 58.099928502780486,
    "risk_level": "low",
    "estimated_apy": 6.199857005560976,
    "tvl": 7631247.425057248,
    "utilization": 0.6597315107975678,
    "pool_name": "USDC Lending Pool",
    "pool_data": {
      "pool_id": "USDC-LENDING",
      "name": "USDC Lending Pool",
      "tvl": 7631247.425057248,
      "apy": 6.199857005560976,
      "borrow_apy": 9.799773976531865,
      "utilization": 0.6597315107975678,
      "collateral_factor": 0.9,
      "asset": "USDC",
      "min_deposit": 10,
      "max_deposit": 5000000,
      "liquidation_threshold": 0.92,
      "last_updated": "2025-08-11T23:03:34.620704",
      "source": "blockchain"
    }
  },
  {
    "source": "folks_finance",
    "protocol_name": "Folks Finance",
    "opportunity_type": "lending",
    "description": "Lending pool: USDT Lending Pool",
    "opportunity_score": 57.75626766587953,
    "risk_level": "low",
    "estimated_apy": 5.5125353317590555,
    "tvl": 5912970.664787161,
    "utilization": 0.7072553092950216,
    "pool_name": "USDT Lending Pool",
    "pool_data": {
      "pool_id": "USDT-LENDING",
      "name": "USDT Lending Pool",
      "tvl": 5912970.664787161,
      "apy": 5.5125353317590555,
      "borrow_apy": 8.74402156072126,
      "utilization": 0.7072553092950216,
      "collateral_factor": 0.85,
      "asset": "USDT",
      "min_deposit": 10,
      "max_deposit": 3000000,
      "liquidation_threshold": 0.88,
      "last_updated": "2025-08-11T23:03:34.620713",
      "source": "blockchain"
    }
  }
]